forman/__init__.py
forman/admin.py
forman/apps.py
forman/models.py
forman/tests.py
forman/urls.py
forman/views.py
forman/migrations/0001_initial.py
forman/migrations/0002_auto_20170502_1406.py
forman/migrations/0003_auto_20170503_1110.py
forman/migrations/0004_sumission.py
forman/migrations/0005_auto_20170503_1526.py
forman/migrations/__init__.py
forman-0.1.3.dist-info/DESCRIPTION.rst
forman-0.1.3.dist-info/METADATA
forman-0.1.3.dist-info/RECORD
forman-0.1.3.dist-info/WHEEL
forman-0.1.3.dist-info/metadata.json
forman-0.1.3.dist-info/top_level.txt
migrations/0001_initial.py
migrations/0002_auto_20170502_1406.py
migrations/0003_auto_20170503_1110.py
migrations/0004_sumission.py
migrations/0005_auto_20170503_1526.py
migrations/__init__.py
